[{"__type__":"cc.AnimationClip","_name":"boomBox_0","_duration":0.08333333333333333,"speed":0.2,"curveData":{"comps":{"cc.Sprite":{"spriteFrame":[{"frame":0,"value":{"__uuid__":"e8zXU5CB9I5pBlRGN9dS0j"}},{"frame":0.016666666666666666,"value":{"__uuid__":"27wROKsDhEF4TKKcH7hDpn"}},{"frame":0.03333333333333333,"value":{"__uuid__":"1aWDXqJ+RPAJ0gIrXXIBUO"}},{"frame":0.05,"value":{"__uuid__":"045QIn6NFFAb0bKMLZ68wk"}},{"frame":0.06666666666666667,"value":{"__uuid__":"27wROKsDhEF4TKKcH7hDpn"}}]}}}},{"__type__":"cc.SpriteFrame","content":{"name":"7","texture":"1e0af4a84","rect":[282,402,153,115],"offset":[5.5,54.5],"originalSize":[164,224],"capInsets":[0,0,0,0]}},{"__type__":"cc.SpriteFrame","content":{"name":"6","texture":"1728c5828","rect":[847,525,155,113],"offset":[-0.5,31.5],"originalSize":[164,224],"capInsets":[0,0,0,0]}},{"__type__":"cc.SpriteFrame","content":{"name":"5","texture":"1e0af4a84","rect":[3,458,153,114],"offset":[-4.5,-1],"originalSize":[164,224],"capInsets":[0,0,0,0]}},{"__type__":"cc.SpriteFrame","content":{"name":"3","texture":"1e0af4a84","rect":[269,707,95,119],"offset":[3,-2],"originalSize":[109,123],"rotated":1,"capInsets":[0,0,0,0]}},{"__type__":"cc.SpriteFrame","content":{"name":"8","texture":"1e0af4a84","rect":[469,369,90,29],"offset":[0,0],"originalSize":[90,29],"rotated":1,"capInsets":[0,0,0,0]}},[{"__type__":"cc.Prefab","_name":"box0","data":{"__id__":1}},{"__type__":"cc.Node","_name":"box0","_children":[{"__id__":2}],"_components":[{"__type__":"cc.Sprite","node":{"__id__":1},"_materials":[{"__uuid__":"ecpdLyjvZBwrvm+cedCcQy"}],"_spriteFrame":{"__uuid__":"71daJdUZ9KJpfJyiEe/TL9"}},{"__type__":"cc.Animation","node":{"__id__":1},"_defaultClip":{"__uuid__":"f3qVrvuPRH5YozvLGxM1qm"},"_clips":[{"__uuid__":"f3qVrvuPRH5YozvLGxM1qm"}]},{"__type__":"cc.BoxCollider","node":{"__id__":1},"_size":{"__type__":"cc.Size","width":91,"height":115}},{"__type__":"806e9TsR5VMy7I+1vZ9GNld","node":{"__id__":1},"leaveSpr":{"__uuid__":"57Cq4RPnlCEp15rn8Tah8e"},"coinNum":5,"foodPro":80}],"_prefab":{"__type__":"cc.PrefabInfo","root":{"__id__":1},"asset":{"__uuid__":"c0rUWTRd5AWLHCl22SFObm"},"fileId":"29rBW+EvFKlpYUjgSWcHsv"},"_contentSize":{"__type__":"cc.Size","width":91,"height":115},"_trs":{"__type__":"TypedArray","ctor":"Float64Array","array":[0,0,0,0,0,0,1,1,1,1]},"_groupIndex":6,"groupIndex":6},{"__type__":"cc.Node","_name":"boom","_parent":{"__id__":1},"_components":[{"__type__":"cc.Sprite","node":{"__id__":2},"_materials":[{"__uuid__":"ecpdLyjvZBwrvm+cedCcQy"}]},{"__type__":"cc.Animation","node":{"__id__":2},"_defaultClip":{"__uuid__":"04UYlDIo9IIJx+k27/fk/j"},"_clips":[{"__uuid__":"04UYlDIo9IIJx+k27/fk/j"}]}],"_prefab":{"__type__":"cc.PrefabInfo","root":{"__id__":1},"asset":{"__uuid__":"c0rUWTRd5AWLHCl22SFObm"},"fileId":"daMkq9RcBDobmus+Spa0Ab"},"_trs":{"__type__":"TypedArray","ctor":"Float64Array","array":[0,0,0,0,0,0,1,1,1,1]}}],{"__type__":"cc.SpriteFrame","content":{"name":"4","texture":"1728c5828","rect":[736,375,105,102],"offset":[-29.5,-29],"originalSize":[164,224],"capInsets":[0,0,0,0]}},{"__type__":"cc.AnimationClip","_name":"box_0","_duration":0.08333333333333333,"speed":0.15,"curveData":{"comps":{"cc.Sprite":{"spriteFrame":[{"frame":0,"value":{"__uuid__":"71daJdUZ9KJpfJyiEe/TL9"}},{"frame":0.016666666666666666,"value":{"__uuid__":"fbhfsXPuBOzr9DQAW+4DSY"}},{"frame":0.03333333333333333,"value":{"__uuid__":"f9fiBTrv9JvIsOv5dIk9dM"}},{"frame":0.05,"value":{"__uuid__":"51KanmRkBBjrb1irLK3HkQ"}},{"frame":0.06666666666666667,"value":{"__uuid__":"71daJdUZ9KJpfJyiEe/TL9"}}]}}}},{"__type__":"cc.SpriteFrame","content":{"name":"2","texture":"1e0af4a84","rect":[146,590,100,123],"offset":[-4.5,0],"originalSize":[109,123],"rotated":1,"capInsets":[0,0,0,0]}},{"__type__":"cc.SpriteFrame","content":{"name":"1","texture":"1728c5828","rect":[444,922,99,122],"offset":[5,-0.5],"originalSize":[109,123],"rotated":1,"capInsets":[0,0,0,0]}}]